axolotl/__init__.py
axolotl/algorithms/__init__.py
axolotl/algorithms/autokeras_search.py
axolotl/algorithms/base.py
axolotl/algorithms/bayesian_search.py
axolotl/algorithms/data_driven_search.py
axolotl/algorithms/dummy.py
axolotl/algorithms/random_search.py
axolotl/algorithms/autokeras_integration/__init__.py
axolotl/algorithms/autokeras_integration/block.py
axolotl/algorithms/autokeras_integration/constants.py
axolotl/algorithms/autokeras_integration/mapping.py
axolotl/algorithms/autokeras_integration/steps.py
axolotl/algorithms/tuners/__init__.py
axolotl/algorithms/tuners/bayesian_oracle.py
axolotl/algorithms/tuners/custom_hps.py
axolotl/algorithms/tuners/hyperparameters.py
axolotl/algorithms/tuners/oracle.py
axolotl/algorithms/tuners/random_search_oracle.py
axolotl/algorithms/tuners/tunable_base.py
axolotl/backend/__init__.py
axolotl/backend/base.py
axolotl/backend/ray.py
axolotl/backend/simple.py
axolotl/d3m_grpc/__init__.py
axolotl/d3m_grpc/constants.py
axolotl/d3m_grpc/server.py
axolotl/predefined_pipelines/__init__.py
axolotl/predefined_pipelines/base_preprocessor.py
axolotl/predefined_pipelines/preprocessor.py
axolotl/utils/__init__.py
axolotl/utils/data_problem.py
axolotl/utils/pipeline.py
axolotl/utils/resources.py
axolotl/utils/schemas.py
axolotl/utils/resources/blocklist.json
axolotl/utils/resources/default_pipelines.json
axolotl/utils/resources/scoring_pipeline.yml
axolotl/utils/resources/splitting_pipelines.json
tamu_axolotl-2021.4.8.dist-info/LICENSE
tamu_axolotl-2021.4.8.dist-info/METADATA
tamu_axolotl-2021.4.8.dist-info/WHEEL
tamu_axolotl-2021.4.8.dist-info/top_level.txt
tamu_axolotl-2021.4.8.dist-info/RECORD
