Metadata-Version: 2.1
Name: tamu-axolotl
Version: 2021.4.8
Summary: 2021.04.08
Home-page: UNKNOWN
License: Apache-2.0
Platform: UNKNOWN
Classifier: License :: OSI Approved :: Apache Software License
Provides-Extra: cpu
Provides-Extra: gpu
